README.md
chatgpt_cli/__init__.py
chatgpt_cli/__version__.py
chatgpt_cli/main.py
chatgpt_cli/services/__init__.py
chatgpt_cli/services/chatgpt.py
chatgpt_cli/settings.py
chatgpt_api_cli-0.2.1.dist-info/entry_points.txt
chatgpt_api_cli-0.2.1.dist-info/WHEEL
chatgpt_api_cli-0.2.1.dist-info/METADATA
chatgpt_api_cli-0.2.1.dist-info/RECORD
